README.md
setup.cfg
setup.py
Topsis_Ria_101803231.egg-info/PKG-INFO
Topsis_Ria_101803231.egg-info/SOURCES.txt
Topsis_Ria_101803231.egg-info/dependency_links.txt
Topsis_Ria_101803231.egg-info/requires.txt
Topsis_Ria_101803231.egg-info/top_level.txt
Topsis_package/__init__.py
Topsis_package/topsis.py