Metadata-Version: 2.1
Name: Topsis-Ria-101803231
Version: 0.0.6
Summary: it is package which tells you best value based on the data by using some mathematical calculations
Home-page: https://github.com/Ria017/Topsis_package
Author: Ria
Author-email: rria_be18@thapar.edu
License: UNKNOWN
Platform: UNKNOWN
Classifier: Programming Language :: Python :: 3
Classifier: License :: OSI Approved :: MIT License
Classifier: Operating System :: OS Independent
Requires-Python: >=3.6
